carl_ff/__init__.py
carl_ff/carl_ff.py
carl_ff/main.py
carl_ff-1.0.0.dist-info/METADATA
carl_ff-1.0.0.dist-info/WHEEL
carl_ff-1.0.0.dist-info/entry_points.txt
carl_ff-1.0.0.dist-info/licenses/LICENSE
carl_ff-1.0.0.dist-info/RECORD
