Metadata-Version: 2.4
Name: carl-ff
Version: 1.0.0
Summary: Firefox ClientAuthenticationRememberList Parser
Project-URL: Homepage, https://github.com/qtc-de/carl-ff
Project-URL: Documentation, https://github.com/qtc-de/carl-ff
Project-URL: Repository, https://github.com/qtc-de/carl-ff
Project-URL: Bug Tracker, https://github.com/qtc-de/carl-ff/issues
Project-URL: Changelog, https://github.com/qtc-de/carl-ff/blob/main/CHANGELOG.md
Author: Tobias Neitzel (@qtc_de)
Maintainer: Tobias Neitzel (@qtc_de)
License:                     GNU GENERAL PUBLIC LICENSE
License-File: LICENSE
Keywords: ClientAuthenticationRememberList,carl-ff,firefox
Classifier: License :: OSI Approved :: GNU General Public License v3 (GPLv3)
Classifier: Operating System :: Unix
Classifier: Programming Language :: Python :: 3
Requires-Python: >=3.10
Requires-Dist: cryptography
